harissumcheck/__init__.py
harissumcheck/harissumcheck.py
harissumcheck/number.py
harissumcheck-0.2.dist-info/METADATA
harissumcheck-0.2.dist-info/WHEEL
harissumcheck-0.2.dist-info/top_level.txt
harissumcheck-0.2.dist-info/RECORD
