Metadata-Version: 2.1
Name: harissumcheck
Version: 0.2
Summary: harissumcheck
Home-page: https://github.com/hariskamal43/typosquatting
Author: Haris Kamal
Author-email: hariskamal43@gmail.com
